midas_powerseries/__init__.py
midas_powerseries/meta.py
midas_powerseries/model.py
midas_powerseries/module.py
midas_powerseries/simulator.py
midas_powerseries-2.0.0.dist-info/METADATA
midas_powerseries-2.0.0.dist-info/WHEEL
midas_powerseries-2.0.0.dist-info/top_level.txt
midas_powerseries-2.0.0.dist-info/RECORD
