Metadata-Version: 2.1
Name: midas-powerseries
Version: 2.0.0
Summary: A MIDAS module for a electrical power timeseries simulator.
Author-email: Stephan Balduin <stephan.balduin@offis.de>
Project-URL: Documentation, https://midas-mosaik.gitlab.io/midas
Requires-Python: >=3.8
Requires-Dist: midas-mosaik>=2.0.0
Requires-Dist: mosaik_api
Requires-Dist: numpy
Requires-Dist: polars
Provides-Extra: dev
Requires-Dist: build; extra == "dev"
Requires-Dist: twine; extra == "dev"
Requires-Dist: pytest; extra == "dev"
Requires-Dist: coverage; extra == "dev"
Requires-Dist: ruff; extra == "dev"
